gamdpy/__init__.py
gamdpy/cc_cores_per_SM_dict.py
gamdpy/calculators/__init__.py
gamdpy/calculators/calculator_hydrodynamic_correlations.py
gamdpy/calculators/calculator_hydrodynamic_profile.py
gamdpy/calculators/calculator_radial_distribution.py
gamdpy/calculators/calculator_structure_factor.py
gamdpy/calculators/calculator_widom_insertion.py
gamdpy/configuration/Configuration.py
gamdpy/configuration/__init__.py
gamdpy/configuration/colarray.py
gamdpy/configuration/make_lattice.py
gamdpy/configuration/old_input_output.py
gamdpy/configuration/topology.py
gamdpy/configuration/unit_cells.py
gamdpy/integrators/NPT_Atomic.py
gamdpy/integrators/NPT_Langevin.py
gamdpy/integrators/NVE.py
gamdpy/integrators/NVT.py
gamdpy/integrators/NVT_Langevin.py
gamdpy/integrators/NVU.py
gamdpy/integrators/NVU_RT.py
gamdpy/integrators/SLLOD.py
gamdpy/integrators/__init__.py
gamdpy/integrators/brownian.py
gamdpy/integrators/gradient_descent.py
gamdpy/integrators/integrator.py
gamdpy/interactions/__init__.py
gamdpy/interactions/angles.py
gamdpy/interactions/bonds.py
gamdpy/interactions/dihedrals.py
gamdpy/interactions/gravity.py
gamdpy/interactions/interaction.py
gamdpy/interactions/make_fixed_interactions.py
gamdpy/interactions/nblist.py
gamdpy/interactions/nblist_linked_lists.py
gamdpy/interactions/pair_potential.py
gamdpy/interactions/planar.py
gamdpy/interactions/planar_interactions.py
gamdpy/interactions/relaxtemp.py
gamdpy/interactions/tabulated_pair_potential.py
gamdpy/interactions/tether.py
gamdpy/interactions/potential_functions/LJ_12_6.py
gamdpy/interactions/potential_functions/LJ_12_6_sigma_epsilon.py
gamdpy/interactions/potential_functions/LJ_SF.py
gamdpy/interactions/potential_functions/SAAP.py
gamdpy/interactions/potential_functions/__init__.py
gamdpy/interactions/potential_functions/add_potential_functions.py
gamdpy/interactions/potential_functions/apply_shifted_force_cutoff.py
gamdpy/interactions/potential_functions/apply_shifted_potential_cutoff.py
gamdpy-0.8.2.dist-info/METADATA
gamdpy-0.8.2.dist-info/WHEEL
gamdpy-0.8.2.dist-info/licenses/LICENSE.txt
gamdpy-0.8.2.dist-info/RECORD
