Metadata-Version: 2.4
Name: gamdpy
Version: 0.8.2
Summary: GPU Accelerated Molecular Dynamics in Python 
Project-URL: Repository, https://github.com/ThomasBechSchroeder/gamdpy
Project-URL: Issues, https://github.com/ThomasBechSchroeder/gamdpy/issues
Author: Ulf R. Pedersen, Nick Bailey, Jesper Schmidt Hansen, Lorenzo Costigliola
Author-email: Thomas Schrøder <tbs@ruc.dk>
Maintainer-email: Thomas Schrøder <tbs@ruc.dk>
License-Expression: MIT AND (Apache-2.0 OR BSD-2-Clause)
License-File: LICENSE.txt
Classifier: Development Status :: 4 - Beta
Classifier: Environment :: GPU
Classifier: Framework :: Jupyter
Classifier: Intended Audience :: Education
Classifier: Intended Audience :: Science/Research
Classifier: License :: OSI Approved :: MIT License
Classifier: Operating System :: OS Independent
Classifier: Programming Language :: Python :: 3
Classifier: Topic :: Scientific/Engineering
Classifier: Topic :: Scientific/Engineering :: Chemistry
Classifier: Topic :: Scientific/Engineering :: Physics
Requires-Python: >=3.10
Requires-Dist: h5py
Requires-Dist: matplotlib
Requires-Dist: numba
Requires-Dist: numpy
Requires-Dist: pandas
